
%main <Sangtinas_Public.lua:0,0> (19 instructions, 76 bytes at Proto)
0 param, 4 slot, 1 upvalue, 2 local, 8 constant, 1 function
  1  [-]  GETTABUP  0 0 -1  ; 0 "_ENV" "print"
  2  [2]  LOADK  1 -2  ; "Website: sangtinas.sytes.net"
  3  [2]  CALL  0 2 1
  4  [5]  CLOSURE  0 0  ; org.luaj.vm2.Prototype
  5  [3]  SETTABUP  0 -3 0  ; 0 "_ENV" "encodes" -
  6  [6]  GETTABUP  0 0 -4  ; 0 "_ENV" "gg"
  7  [6]  GETTABLE  0 0 -5  ; "toast"
  8  [6]  LOADK  1 -2  ; "Website: sangtinas.sytes.net"
  9  [6]  CALL  0 2 1
  10  [7]  GETTABUP  0 0 -3  ; 0 "_ENV" "encodes"
  11  [7]  LOADK  1 -6  ; "2859826E5F0D0E111511150D26A01A1727170D0D0D0D0D0D0D0D0D0E11200D0D0D130D4D0D4E4D0D0D2A4D0D0E320D0D0D150D0D8E13CD4D0D140D4E0D4E4D0D0D2A4D0D0E138D4D0D4E4D0E0D2A8D0D0E538D4E0D8D0D0D0D6A8D0D0E93CD4E0DCD0D8D0DAA4D0D0E2C0D8D0D150D0D0D11130D0D0D0D0D0D0D7D7F767B810D112A0D0D0D0D0D0D0D64726F80768172472D806E7B7481767B6E803B80868172803B7B72810D11150D0D0D0D0D0D0D727B707C7172800D11100D0D0D0D0D0D0D74740D11130D0D0D0D0D0D0D817C6E80810D1110180D0D0D0D0D0D404E404E4341443F4353453D4443453E443F41443F51453D4352444F4441453E4443444F4352453D404F453D4543453E443F453D404F444F443F453E3E44445144534443444F453E404240414341443F4353453D4443453E443F41443F51453D4352444F4441453E4443444F4352453D404F453D4543453E443F453D404F444F443F453E404140433E444440453F444F443D453E44434450444F3F51443F444F443D4450443E443F453D4042443D4450443E443F40433E443F513F513F514453443F453E453F4453444F3F514042443D4450443E443F41444441453D453F435340424041404F404F404140463F514440453F444F443D453E44434450444F3F514042444240433F514453443F453E453F4453444F3F51453D453E44534443444F4441404F443D44424352445340424042453E4450444F453F444E4353443F445340424442404640524140404340454053413F4140404E4052413D3F5140453F5141434143414341434143414340444053413F41404043403F4053413F414040433F51443F444F443E404340433E44443F444F443E3E4444414441404F453E44504352453D453E404240414341443F4353453D4443453E443F41443F51453D4352444F4441453E4443444F4352453D404F453D4543453E443F453D404F444F443F453E404140433E4444464450443D435244463F51443E4352453E43523F51414E3F51443F444F443D4450443E443F453D4042404140534142413F4143414240534140423F413F42404051423E4051423F405240524052413F405240524052413F4051423E4053414041524051405241524052414140534141405241414051423E4051423E4051423E4051423E4051423E4051423E4051423E4051423E4051423E4051423F405142404052413D4051423E4051423E4051423E4052413F413E423E413E423E4142423E413D40534051423E4051423E4051423E4052413F4051423E4051423E4142423F4052413D4142423E413E423E4051423E40534152413E423E4142423E4051423E4053423D4051423E4142423E4051423E405240514051423E4051423E4051423E405240524052413F4051423E4051423E4051423E4051423E4051423E4051423E4051423E4142413D414140534141424041424051414141404141423D414141534051423E405240514051423E4051423E4051423E4051423E4051423E4051423E4240423E413E423D40524052405241414051423E4051423E4051423E4051423E4051423E4051423E4051423E414240514140423F414141534141413E4142405241414140414141534140423F414240514051423E4051423F4051423E4051423E4051423E405240514051423E4051423E4051423E4052413D4051423E4051423E4051423E4051423E4051423E40524052405241524051423E4051423E4051423E4052413D4051423E413E423E4051423E413F413D413E423E413E423E4051423E4143413D4142423E413E423E4051423E4143413E423D423E413E423E4051423F423D423F4051423E4051423F4051423E415241524142423E4051423E4051423F4143413E413E423E413E423F4051423F414041524051423E4051423E4051423F405341524142423E4051423E4051423E413E423E4051423E4051423E4051423E414041534051423E4142423E4051423E4140423D4051423E4051423E4051423E4053423D4051423E4142423E4051423E4052413D4051423E4051423E4051423E405240524052413E4051423E4051423E4051423E4051423E4051423E4051423E4051423E4140423F41424051414240514141405341414240414240524051423E40524052405240534051423E4051423E4051423E4051423E4051423E4051423E4051423E414141434141423D4140423F414140524051423E40524052405240514051423E4051423E4051423E4051423E4051423E4051423E4051423E4141413E4141413E4051423E40524052405241434051423E4051423E4051423E4051423E4051423E4051423E4051423E414141524140423F4141414241414053413F4240414140534141423F414240534141405341424051414240524051423E40524052413E41404051423E4051423E4051423E4051423E4051423E4051423E4051423E4141413F41424052414240524141423E413E4141413D423D413D423D414240514140423F414141534141413E4142405241414140414141534140423F41424051413D41534142405141424140414240524141405341424051413D4153414141534141405341424052413D423D4141423E4142405341404240414141434141414041414051413D423D413F423E41424053414042404141414341414140414140514140423D413E423F41424053414240524141423D414040534141423E414140524140423F4142405241414053413D41534141413F4142405241414152414141434051423E405240524052413F4051423E4051423E4051423E4051423E4051423E4051423E4051423E414140514141423D41414153414240524141405341414153414240524051423E4051423E4051423E4051423E4051423E4051423F4051423E4051423E4051423E4051423E4051423E4053413D4051423E4051423E4051423E4051423E4051423E4051423E4051423E413E423E414040514140423F414141534141413E4142405241414140414141534140423F414240514140423D413F423E4142405341404240414141434141414041414051413D415341414143414240534140423F4051423E405241524051423E4051423E4051423E405240524051423E4051423E4051423E405240524051423E4051423E4051423E405240524051423E4051423E4051423E405240524051423E4051423E4051423E405240524051423E4051423E4051423E405240524051423E4051423E4051423E405240524051423E4051423E4051423E405240524051423E4051423E4051423E405240524051423E4051423E4051423E405240534051423E4051423E4051423E405240534051423E4051423E4051423E405240534051423E4051423E4051423E4052413D4051423E4051423E4051423E4051423F4051423E4051423E4051423E4052413F4051423E4051423E4051423E4051423E4051423E4051423E4051423E4140423F414240524142405241414053414141524141423E414240524051423E405241404051423E4051423E4051423E405241524051423E4051423E4051423E4051423F4051423E4051423E4051423E405240534051423E4051423E4051423E4051423E4051423E4051423E4051423E4140423D413F4053413F41534140413D4051423E4051423F4051423E4051423E4051423E4051423F4051423E4053413D4051423E4051423E4051423E4051423E4051423E4051423E4051423E413E423E414040514140423F414141534141413E4142405241414140414141534140423F414240514140423D413F423E4142405341404240414141434141414041414051413D415341414143414240534140423F4051423E4052413D4051423E4051423E4051423E405142404051423E4051423E4051423E4052413D4051423E4051423E4051423E405240514051423E4051423E4051423E4052413E4051423E4051423E4051423E4052413E4051423E4051423E4051423E4052413E4051423E4051423E4051423E4051423E4051423E4051423E4051423E4051423F4051423E4051423E4051423E405240534051423E4051423E4051423E4051423E4051423E4051423E4051423E4140423D413F4053413F41534140413D4051423E404140433E4444464450443D435244463F51443F444F443D3F51414E3F51444644504352443E4042443E4352453E435240433E444451443D4352444644464042443F444F443D40433E440D11120D0D0D0D0D0D0D797C6E710D11130D0D0D0D0D0D0D7D706E79790D0E0D0D0D100D0D0D120D0D0D0E0D12130D0D0D590D4D0DCE4D0D0D320E0D0D6A8D0D0F6C0D0D0E2C0D8D0D0F0D0D0D11120D0D0D0D0D0D0D7480826F0D11100D0D0D0D0D0D0D3B3B0D0E0D0D0D110D0D0D110D0D0D0E0D121A0D0D0D530D4D0D544DCD0D938D4D0DCD0D0D0D0ECE0D0DAA8D8D0E9A0D4E0E9B4D4E0E9A8D4E0E9E0D4E0E6B0D0D0E6C0D0D0D2C0D8D0D140D0D0D11140D0D0D0D0D0D0D80817F767B740D11120D0D0D0D0D0D0D70756E7F0D11160D0D0D0D0D0D0D817C7B827A6F727F0D100D0D0D0D0D0D3D4D100D0D0D0D0D0D7D4D100D0D0D0D0D0D374D100D0D0D0D8B91BB4E0D0D0D0D0E0D0D0D0D0D230D0D0D0D0D0D0D4D606E7B7481767B6E806C5D826F7976703B79826E0D1A0D0D0D110D0D0D110D0D0D110D0D0D110D0D0D110D0D0D110D0D0D110D0D0D110D0D0D110D0D0D110D0D0D110D0D0D110D0D0D110D0D0D0E0D0D0D0F0D0D0D0D0D0D0D750D0D0D0D0D1A0D0D0D0E0D0D0D120D0D0D0D0D0D0D6C525B630D0E0D0D0D0D0D230D0D0D0D0D0D0D4D606E7B7481767B6E806C5D826F7976703B79826E0D130D0D0D110D0D0D110D0D0D110D0D0D110D0D0D110D0D0D120D0D0D0E0D0D0D120D0D0D0D0D0D0D707C71720D0D0D0D0D130D0D0D0E0D0D0D120D0D0D0D0D0D0D6C525B630D0E0D0D0D0E0D230D0D0D0D0D0D0D4D606E7B7481767B6E806C5D826F7976703B79826E0D200D0D0D0F0D0D0D0F0D0D0D0F0D0D0D120D0D0D100D0D0D130D0D0D130D0D0D130D0D0D130D0D0D140D0D0D140D0D0D140D0D0D150D0D0D150D0D0D150D0D0D160D0D0D160D0D0D160D0D0D160D0D0D0F0D0D0D120D0D0D0D0D0D0D716E816E0D190D0D0D200D0D0D110D0D0D0D0D0D0D727B700D1C0D0D0D200D0D0D0E0D0D0D120D0D0D0D0D0D0D6C525B630D"
  12  [7]  CALL  0 2 2
  13  [8]  GETTABUP  1 0 -7  ; 0 "_ENV" "load"
  14  [8]  MOVE  2 0
  15  [8]  CALL  1 2 2
  16  [9]  GETTABUP  2 0 -8  ; 0 "_ENV" "pcall"
  17  [9]  MOVE  3 1
  18  [9]  CALL  2 2 1
  19  [9]  RETURN  0 1
constants (8) for Proto:
  1  "print"
  2  "Website: sangtinas.sytes.net"
  3  "encodes"
  4  "gg"
  5  "toast"
  6  "2859826E5F0D0E111511150D26A01A1727170D0D0D0D0D0D0D0D0D0E11200D0D0D130D4D0D4E4D0D0D2A4D0D0E320D0D0D150D0D8E13CD4D0D140D4E0D4E4D0D0D2A4D0D0E138D4D0D4E4D0E0D2A8D0D0E538D4E0D8D0D0D0D6A8D0D0E93CD4E0DCD0D8D0DAA4D0D0E2C0D8D0D150D0D0D11130D0D0D0D0D0D0D7D7F767B810D112A0D0D0D0D0D0D0D64726F80768172472D806E7B7481767B6E803B80868172803B7B72810D11150D0D0D0D0D0D0D727B707C7172800D11100D0D0D0D0D0D0D74740D11130D0D0D0D0D0D0D817C6E80810D1110180D0D0D0D0D0D404E404E4341443F4353453D4443453E443F41443F51453D4352444F4441453E4443444F4352453D404F453D4543453E443F453D404F444F443F453E3E44445144534443444F453E404240414341443F4353453D4443453E443F41443F51453D4352444F4441453E4443444F4352453D404F453D4543453E443F453D404F444F443F453E404140433E444440453F444F443D453E44434450444F3F51443F444F443D4450443E443F453D4042443D4450443E443F40433E443F513F513F514453443F453E453F4453444F3F514042443D4450443E443F41444441453D453F435340424041404F404F404140463F514440453F444F443D453E44434450444F3F514042444240433F514453443F453E453F4453444F3F51453D453E44534443444F4441404F443D44424352445340424042453E4450444F453F444E4353443F445340424442404640524140404340454053413F4140404E4052413D3F5140453F5141434143414341434143414340444053413F41404043403F4053413F414040433F51443F444F443E404340433E44443F444F443E3E4444414441404F453E44504352453D453E404240414341443F4353453D4443453E443F41443F51453D4352444F4441453E4443444F4352453D404F453D4543453E443F453D404F444F443F453E404140433E4444464450443D435244463F51443E4352453E43523F51414E3F51443F444F443D4450443E443F453D4042404140534142413F4143414240534140423F413F42404051423E4051423F405240524052413F405240524052413F4051423E4053414041524051405241524052414140534141405241414051423E4051423E4051423E4051423E4051423E4051423E4051423E4051423E4051423E4051423F405142404052413D4051423E4051423E4051423E4052413F413E423E413E423E4142423E413D40534051423E4051423E4051423E4052413F4051423E4051423E4142423F4052413D4142423E413E423E4051423E40534152413E423E4142423E4051423E4053423D4051423E4142423E4051423E405240514051423E4051423E4051423E405240524052413F4051423E4051423E4051423E4051423E4051423E4051423E4051423E4142413D414140534141424041424051414141404141423D414141534051423E405240514051423E4051423E4051423E4051423E4051423E4051423E4240423E413E423D40524052405241414051423E4051423E4051423E4051423E4051423E4051423E4051423E414240514140423F414141534141413E4142405241414140414141534140423F414240514051423E4051423F4051423E4051423E4051423E405240514051423E4051423E4051423E4052413D4051423E4051423E4051423E4051423E4051423E40524052405241524051423E4051423E4051423E4052413D4051423E413E423E4051423E413F413D413E423E413E423E4051423E4143413D4142423E413E423E4051423E4143413E423D423E413E423E4051423F423D423F4051423E4051423F4051423E415241524142423E4051423E4051423F4143413E413E423E413E423F4051423F414041524051423E4051423E4051423F405341524142423E4051423E4051423E413E423E4051423E4051423E4051423E414041534051423E4142423E4051423E4140423D4051423E4051423E4051423E4053423D4051423E4142423E4051423E4052413D4051423E4051423E4051423E405240524052413E4051423E4051423E4051423E4051423E4051423E4051423E4051423E4140423F41424051414240514141405341414240414240524051423E40524052405240534051423E4051423E4051423E4051423E4051423E4051423E4051423E414141434141423D4140423F414140524051423E40524052405240514051423E4051423E4051423E4051423E4051423E4051423E4051423E4141413E4141413E4051423E40524052405241434051423E4051423E4051423E4051423E4051423E4051423E4051423E414141524140423F4141414241414053413F4240414140534141423F414240534141405341424051414240524051423E40524052413E41404051423E4051423E4051423E4051423E4051423E4051423E4051423E4141413F41424052414240524141423E413E4141413D423D413D423D414240514140423F414141534141413E4142405241414140414141534140423F41424051413D41534142405141424140414240524141405341424051413D4153414141534141405341424052413D423D4141423E4142405341404240414141434141414041414051413D423D413F423E41424053414042404141414341414140414140514140423D413E423F41424053414240524141423D414040534141423E414140524140423F4142405241414053413D41534141413F4142405241414152414141434051423E405240524052413F4051423E4051423E4051423E4051423E4051423E4051423E4051423E414140514141423D41414153414240524141405341414153414240524051423E4051423E4051423E4051423E4051423E4051423F4051423E4051423E4051423E4051423E4051423E4053413D4051423E4051423E4051423E4051423E4051423E4051423E4051423E413E423E414040514140423F414141534141413E4142405241414140414141534140423F414240514140423D413F423E4142405341404240414141434141414041414051413D415341414143414240534140423F4051423E405241524051423E4051423E4051423E405240524051423E4051423E4051423E405240524051423E4051423E4051423E405240524051423E4051423E4051423E405240524051423E4051423E4051423E405240524051423E4051423E4051423E405240524051423E4051423E4051423E405240524051423E4051423E4051423E405240524051423E4051423E4051423E405240524051423E4051423E4051423E405240534051423E4051423E4051423E405240534051423E4051423E4051423E405240534051423E4051423E4051423E4052413D4051423E4051423E4051423E4051423F4051423E4051423E4051423E4052413F4051423E4051423E4051423E4051423E4051423E4051423E4051423E4140423F414240524142405241414053414141524141423E414240524051423E405241404051423E4051423E4051423E405241524051423E4051423E4051423E4051423F4051423E4051423E4051423E405240534051423E4051423E4051423E4051423E4051423E4051423E4051423E4140423D413F4053413F41534140413D4051423E4051423F4051423E4051423E4051423E4051423F4051423E4053413D4051423E4051423E4051423E4051423E4051423E4051423E4051423E413E423E414040514140423F414141534141413E4142405241414140414141534140423F414240514140423D413F423E4142405341404240414141434141414041414051413D415341414143414240534140423F4051423E4052413D4051423E4051423E4051423E405142404051423E4051423E4051423E4052413D4051423E4051423E4051423E405240514051423E4051423E4051423E4052413E4051423E4051423E4051423E4052413E4051423E4051423E4051423E4052413E4051423E4051423E4051423E4051423E4051423E4051423E4051423E4051423F4051423E4051423E4051423E405240534051423E4051423E4051423E4051423E4051423E4051423E4051423E4140423D413F4053413F41534140413D4051423E404140433E4444464450443D435244463F51443F444F443D3F51414E3F51444644504352443E4042443E4352453E435240433E444451443D4352444644464042443F444F443D40433E440D11120D0D0D0D0D0D0D797C6E710D11130D0D0D0D0D0D0D7D706E79790D0E0D0D0D100D0D0D120D0D0D0E0D12130D0D0D590D4D0DCE4D0D0D320E0D0D6A8D0D0F6C0D0D0E2C0D8D0D0F0D0D0D11120D0D0D0D0D0D0D7480826F0D11100D0D0D0D0D0D0D3B3B0D0E0D0D0D110D0D0D110D0D0D0E0D121A0D0D0D530D4D0D544DCD0D938D4D0DCD0D0D0D0ECE0D0DAA8D8D0E9A0D4E0E9B4D4E0E9A8D4E0E9E0D4E0E6B0D0D0E6C0D0D0D2C0D8D0D140D0D0D11140D0D0D0D0D0D0D80817F767B740D11120D0D0D0D0D0D0D70756E7F0D11160D0D0D0D0D0D0D817C7B827A6F727F0D100D0D0D0D0D0D3D4D100D0D0D0D0D0D7D4D100D0D0D0D0D0D374D100D0D0D0D8B91BB4E0D0D0D0D0E0D0D0D0D0D230D0D0D0D0D0D0D4D606E7B7481767B6E806C5D826F7976703B79826E0D1A0D0D0D110D0D0D110D0D0D110D0D0D110D0D0D110D0D0D110D0D0D110D0D0D110D0D0D110D0D0D110D0D0D110D0D0D110D0D0D110D0D0D0E0D0D0D0F0D0D0D0D0D0D0D750D0D0D0D0D1A0D0D0D0E0D0D0D120D0D0D0D0D0D0D6C525B630D0E0D0D0D0D0D230D0D0D0D0D0D0D4D606E7B7481767B6E806C5D826F7976703B79826E0D130D0D0D110D0D0D110D0D0D110D0D0D110D0D0D110D0D0D120D0D0D0E0D0D0D120D0D0D0D0D0D0D707C71720D0D0D0D0D130D0D0D0E0D0D0D120D0D0D0D0D0D0D6C525B630D0E0D0D0D0E0D230D0D0D0D0D0D0D4D606E7B7481767B6E806C5D826F7976703B79826E0D200D0D0D0F0D0D0D0F0D0D0D0F0D0D0D120D0D0D100D0D0D130D0D0D130D0D0D130D0D0D130D0D0D140D0D0D140D0D0D140D0D0D150D0D0D150D0D0D150D0D0D160D0D0D160D0D0D160D0D0D160D0D0D0F0D0D0D120D0D0D0D0D0D0D716E816E0D190D0D0D200D0D0D110D0D0D0D0D0D0D727B700D1C0D0D0D200D0D0D0E0D0D0D120D0D0D0D0D0D0D6C525B630D"
  7  "load"
  8  "pcall"
locals (2) for Proto:
  0  data 13 20
  1  enc 16 20
upvalues (1) for Proto:
  0  0 instack _ENV

%function <Sangtinas_Public.lua:3,5> (6 instructions, 24 bytes at Proto)
1 param, 5 slot, 1 upvalue, 1 local, 2 constant, 1 function
  1  [-]  SELF  1 0 -1  ; "gsub"
  2  [4]  LOADK  3 -2  ; ".."
  3  [4]  CLOSURE  4 0  ; org.luaj.vm2.Prototype
  4  [4]  CALL  1 4 2
  5  [4]  RETURN  1 2
  6  [5]  RETURN  0 1 ; unused
constants (2) for Proto:
  1  "gsub"
  2  ".."
locals (1) for Proto:
  0  code 1 7
upvalues (1) for Proto:
  0  0 closed _ENV

%function <Sangtinas_Public.lua:4,4> (13 instructions, 52 bytes at Proto)
1 param, 5 slot, 1 upvalue, 1 local, 7 constant, 0 function
  1  [-]  GETTABUP  1 0 -1  ; 0 "_ENV" "string"
  2  [4]  GETTABLE  1 1 -2  ; "char"
  3  [4]  GETTABUP  2 0 -3  ; 0 "_ENV" "tonumber"
  4  [4]  MOVE  3 0
  5  [4]  LOADK  4 -4  ; 16
  6  [4]  CALL  2 3 2
  7  [4]  ADD  2 2 -5  ; - 256
  8  [4]  SUB  2 2 -6  ; - 13
  9  [4]  ADD  2 2 -7  ; - 255999744
  10  [4]  MOD  2 2 -5
  11  [4]  TAILCALL  1 2 0
  12  [4]  RETURN  1 0 ; unused
  13  [4]  RETURN  0 1 ; unused
constants (7) for Proto:
  1  "string"
  2  "char"
  3  "tonumber"
  4  16
  5  256
  6  13
  7  255999744
locals (1) for Proto:
  0  h 1 14
upvalues (1) for Proto:
  0  0 closed _ENV
